{
  "project_info": {
    "project_number": "615401099800",
    "project_id": "featherfinder-f0507",
    "storage_bucket": "featherfinder-f0507.appspot.com"
  },
  "client": [
    {
      "client_info": {
        "mobilesdk_app_id": "1:615401099800:android:68e9298fd3dabcc6b1696d",
        "android_client_info": {
          "package_name": "com.ryanblignaut.featherfinder"
        }
      },
      "oauth_client": [
        {
          "client_id": "615401099800-71q0msscfin8o6p8jcu6h9en3mfr83aa.apps.googleusercontent.com",
          "client_type": 3
        }
      ],
      "api_key": [
        {
          "current_key": "AIzaSyDrEg901IGh_QXyRZOBiKOOty88us3FO-M"
        }
      ],
      "services": {
        "appinvite_service": {
          "other_platform_oauth_client": [
            {
              "client_id": "615401099800-71q0msscfin8o6p8jcu6h9en3mfr83aa.apps.googleusercontent.com",
              "client_type": 3
            }
          ]
        }
      }
    }
  ],
  "configuration_version": "1"
}